protean_elasticsearch/__init__.py
protean_elasticsearch/__main__.py
protean_elasticsearch/cli.py
protean_elasticsearch/repository.py
protean_elasticsearch-0.0.6.dist-info/METADATA
protean_elasticsearch-0.0.6.dist-info/RECORD
protean_elasticsearch-0.0.6.dist-info/WHEEL
protean_elasticsearch-0.0.6.dist-info/entry_points.txt
protean_elasticsearch-0.0.6.dist-info/top_level.txt
