Metadata-Version: 2.1
Name: protean-elasticsearch
Version: 0.0.6
Summary: Protean Elasticsearch Extension
Home-page: https://github.com/proteanhq/protean-elasticsearch
Author: Subhash Bhushan C
Author-email: subhash@team8solutions.com
License: BSD 3-Clause License
Platform: UNKNOWN
Classifier: Development Status :: 2 - Pre-Alpha
Classifier: Intended Audience :: Developers
Classifier: License :: OSI Approved :: BSD License
Classifier: Operating System :: Unix
Classifier: Operating System :: POSIX :: Linux
Classifier: Operating System :: OS/2
Classifier: Programming Language :: Python
Classifier: Programming Language :: Python :: 3.6
Classifier: Programming Language :: Python :: 3 :: Only
Classifier: Topic :: Database
Classifier: Topic :: Software Development :: Libraries
Classifier: Topic :: Software Development :: Libraries :: Application Frameworks
Classifier: Topic :: Software Development :: Libraries :: Python Modules
Requires-Dist: click (==7.0)
Requires-Dist: elasticsearch (>=6.1.0)
Requires-Dist: elasticsearch-dsl (>=6.1.0)
Requires-Dist: protean (==0.0.5)
